suruguya/__init__.py
suruguya/suruguya.py
suruguya-0.0.2.dist-info/LICENSE
suruguya-0.0.2.dist-info/METADATA
suruguya-0.0.2.dist-info/WHEEL
suruguya-0.0.2.dist-info/top_level.txt
suruguya-0.0.2.dist-info/RECORD
