Metadata-Version: 2.1
Name: suruguya
Version: 0.0.2
Summary: suruguya api-like wrapper
Home-page: https://bitbucket.org/marvinody/suruguya/
Author: marvinody
Author-email: manny@sadpanda.moe
License: UNKNOWN
Platform: UNKNOWN
Classifier: Programming Language :: Python :: 3.5
Requires-Dist: beautifulsoup4 (==4.7.1)
Requires-Dist: certifi (==2019.3.9)
Requires-Dist: chardet (==3.0.4)
Requires-Dist: idna (==2.8)
Requires-Dist: requests (==2.21.0)
Requires-Dist: soupsieve (==1.9)
Requires-Dist: urllib3 (==1.24.1)
